[
  {
    "title": "Quine",
    "descr": [
      "Technically, every irreducible combinator is a quine, for it returns itself. ",
      "Write a combinator that returns itself when given <i>any</i> argument."
    ],
    "subst": "&phi;",
    "cases": [
      [ "phi", "phi x", "phi" ],
      [ "phi", "phi x y z", "phi" ]
    ]
  },
  {
    "title": "Literal foo",
    "descr": [
      "You are given a term <code>foo</code>.",
      "Construct f such that <code>f x = foo(f, x)</code> for any given <code>x</code>."
    ],
    "vars": ["foo"],
    "subst": "&phi;",
    "cases": [
      [ "phi", "phi x", "foo phi x"]
    ]
  }
]
